aaron_add_mcp/__init__.py
aaron_add_mcp-0.1.0.dist-info/WHEEL
aaron_add_mcp-0.1.0.dist-info/entry_points.txt
aaron_add_mcp-0.1.0.dist-info/METADATA
aaron_add_mcp-0.1.0.dist-info/RECORD
